evals/__init__.py
evals/api.py
evals/base.py
evals/data.py
evals/eval.py
evals/formatting.py
evals/metrics.py
evals/record.py
evals/registry.py
evals/registry_test.py
evals/cli/oaieval.py
evals/cli/oaievalset.py
evals/completion_fns/__init__.py
evals/completion_fns/cot.py
evals/completion_fns/langchain_llm.py
evals/completion_fns/langchain_math.py
evals/completion_fns/openai.py
evals/completion_fns/retrieval.py
evals/elsuite/lambada.py
evals/elsuite/multiple_choice.py
evals/elsuite/translate.py
evals/elsuite/utils.py
evals/elsuite/utils_test.py
evals/elsuite/basic/fuzzy_match.py
evals/elsuite/basic/fuzzy_match_test.py
evals/elsuite/basic/includes.py
evals/elsuite/basic/includes_test.py
evals/elsuite/basic/json_validator.py
evals/elsuite/basic/json_validator_test.py
evals/elsuite/basic/match.py
evals/elsuite/basic/match_test.py
evals/elsuite/modelgraded/base.py
evals/elsuite/modelgraded/classify.py
evals/elsuite/modelgraded/classify_utils.py
evals/elsuite/test/match.py
evals/prompt/base.py
evals/registry/completion_fns/cot.yaml
evals/registry/completion_fns/langchain_chains.yaml
evals/registry/completion_fns/langchain_llms.yaml
evals/registry/eval_sets/chinese-numbers.yaml
evals/registry/eval_sets/coqa-ex.yaml
evals/registry/eval_sets/css-selectors.yaml
evals/registry/eval_sets/logiqa-logical-reasoning-plus.yaml
evals/registry/eval_sets/manga-translation.yaml
evals/registry/eval_sets/mazes.yaml
evals/registry/eval_sets/pointer-value-retrieval.yaml
evals/registry/eval_sets/raven-matrices.yaml
evals/registry/eval_sets/stock-options.yaml
evals/registry/eval_sets/test-all.yaml
evals/registry/eval_sets/test-basic.yaml
evals/registry/eval_sets/test-modelgraded.yaml
evals/registry/eval_sets/ukraine-gec.yaml
evals/registry/eval_sets/word-associations.yaml
evals/registry/evals/2d_movement.yaml
evals/registry/evals/3d_globe_movement.yaml
evals/registry/evals/3d_object_manipulation.yaml
evals/registry/evals/Chinese_character_riddles.yaml
evals_nightly-1.0.3.dev20230807.dist-info/LICENSE
evals_nightly-1.0.3.dev20230807.dist-info/METADATA
evals_nightly-1.0.3.dev20230807.dist-info/WHEEL
evals_nightly-1.0.3.dev20230807.dist-info/entry_points.txt
evals_nightly-1.0.3.dev20230807.dist-info/top_level.txt
evals_nightly-1.0.3.dev20230807.dist-info/RECORD
