Metadata-Version: 2.1
Name: evals-nightly
Version: 1.0.3.dev20230807
Requires-Python: >=3.9
License-File: LICENSE
Requires-Dist: mypy
Requires-Dist: openai >=0.27.2
Requires-Dist: tiktoken
Requires-Dist: blobfile
Requires-Dist: backoff
Requires-Dist: numpy
Requires-Dist: snowflake-connector-python[pandas]
Requires-Dist: pandas
Requires-Dist: datasets
Requires-Dist: fire
Requires-Dist: pydantic
Requires-Dist: tqdm
Requires-Dist: nltk
Requires-Dist: filelock
Requires-Dist: mock
Requires-Dist: langdetect
Requires-Dist: termcolor
Requires-Dist: lz4
Requires-Dist: pyzstd
Requires-Dist: pyyaml
Requires-Dist: sacrebleu
Requires-Dist: matplotlib
Requires-Dist: pytest
Requires-Dist: setuptools-scm
Requires-Dist: langchain
Requires-Dist: types-PyYAML
Provides-Extra: formatters
Requires-Dist: black ; extra == 'formatters'
Requires-Dist: isort ; extra == 'formatters'
Requires-Dist: autoflake ; extra == 'formatters'
